kinematicfunctions/__init__.py
kinematicfunctions/example.py
Spacecraft_Attitude_Dynamics_Functions-0.0.5.dist-info/LICENSE.txt
Spacecraft_Attitude_Dynamics_Functions-0.0.5.dist-info/METADATA
Spacecraft_Attitude_Dynamics_Functions-0.0.5.dist-info/WHEEL
Spacecraft_Attitude_Dynamics_Functions-0.0.5.dist-info/top_level.txt
Spacecraft_Attitude_Dynamics_Functions-0.0.5.dist-info/RECORD
