Metadata-Version: 2.1
Name: Spacecraft-Attitude-Dynamics-Functions
Version: 0.0.5
Summary: Functions for Attitude Dynamics
Home-page: https://shivbc.com/
Author: Shivam Bhatia
Author-email: shivbhatia19@gmail.com
License: MIT
Keywords: Dynamics
Platform: UNKNOWN
Classifier: Development Status :: 5 - Production/Stable
Classifier: Intended Audience :: Education
Classifier: Operating System :: OS Independent
Classifier: License :: OSI Approved :: MIT License
Classifier: Programming Language :: Python :: 3
License-File: LICENSE.txt
Requires-Dist: numpy
Requires-Dist: scipy
Requires-Dist: sympy
Requires-Dist: matplotlib
